[
    {
        "name": "fse",
        "age": 43,
        "region": "auvergne-rhone-alpes",
        "satisfaction": "oui",
        "timestamp": "2024-11-24 16:13:58"
    },
    {
        "name": "erah",
        "age": 16,
        "region": "ile-de-france",
        "satisfaction": "oui",
        "timestamp": "2024-11-24 16:24:32"
    },
    {
        "name": "fioezgjzrpb",
        "age": 78,
        "region": "ile-de-france",
        "satisfaction": "non",
        "timestamp": "2024-11-29 11:16:09"
    },
    {
        "name": "fd",
        "age": 18,
        "region": "ile-de-france",
        "environment": "urbain",
        "employment": "formation",
        "social_activities": "reguliere",
        "life_quality": 8,
        "health_issues": "non",
        "support_type": "moral",
        "daily_issues": "vcbv",
        "timestamp": "2024-12-09 13:43:15"
    }
]